{
  "symbol": "AIM",
  "generatedAt": 1779976800000,
  "metadata": {
    "providerByTimeframe": {
      "daily": "stub",
      "4h": "stub",
      "5m": "stub"
    },
    "dataQualityFlags": [],
    "freshness": "fresh",
    "referencePrice": 0.373
  },
  "majorSupport": [
    {
      "id": "AIM-support-zone-1",
      "symbol": "AIM",
      "kind": "support",
      "timeframeBias": "mixed",
      "zoneLow": 0.21,
      "zoneHigh": 0.21,
      "representativePrice": 0.21,
      "strengthScore": 26.66,
      "strengthLabel": "strong",
      "touchCount": 2,
      "confluenceCount": 2,
      "sourceTypes": [
        "swing_low"
      ],
      "timeframeSources": [
        "daily",
        "4h"
      ],
      "reactionQualityScore": 0.2084,
      "rejectionScore": 0.1851,
      "displacementScore": 0.9797,
      "sessionSignificanceScore": 0.85,
      "followThroughScore": 0.8571,
      "gapContinuationScore": 0.976,
      "sourceEvidenceCount": 2,
      "firstTimestamp": 1779249600000,
      "lastTimestamp": 1779292800000,
      "isExtension": false,
      "freshness": "stale",
      "notes": [
        "Derived from daily support swing.",
        "displacement=1.0698",
        "reactions=1",
        "rejection=0.1948",
        "followThrough=0.8856",
        "gapContinuation=1.0000",
        "gap=yes",
        "Derived from 4h support swing.",
        "displacement=0.7444",
        "rejection=0.1754",
        "followThrough=0.8285",
        "gapContinuation=0.9521",
        "freshness=stale",
        "evidence=2",
        "rejection=0.1851",
        "followThrough=0.8571",
        "gapContinuation=0.9760",
        "pathClearance=1.0000",
        "crowdingPenalty=1.0000",
        "recycledPenalty=1.0000"
      ]
    }
  ],
  "majorResistance": [
    {
      "id": "AIM-resistance-zone-14",
      "symbol": "AIM",
      "kind": "resistance",
      "timeframeBias": "mixed",
      "zoneLow": 0.5358,
      "zoneHigh": 0.5392,
      "representativePrice": 0.5392,
      "strengthScore": 42.26,
      "strengthLabel": "major",
      "touchCount": 15,
      "confluenceCount": 2,
      "sourceTypes": [
        "swing_high"
      ],
      "timeframeSources": [
        "4h",
        "daily"
      ],
      "reactionQualityScore": 0.3631,
      "rejectionScore": 0.4157,
      "displacementScore": 0.0706,
      "sessionSignificanceScore": 0.7,
      "followThroughScore": 0.5571,
      "gapContinuationScore": 0.4639,
      "sourceEvidenceCount": 5,
      "firstTimestamp": 1777262400000,
      "lastTimestamp": 1777651200000,
      "isExtension": false,
      "freshness": "stale",
      "notes": [
        "Derived from 4h resistance swing.",
        "displacement=0.0435",
        "reactions=1",
        "rejection=0.3534",
        "followThrough=0.5466",
        "gapContinuation=1.0000",
        "gap=yes",
        "displacement=0.0735",
        "reactions=2",
        "rejection=0.3518",
        "followThrough=0.5352",
        "gapContinuation=0.0000",
        "gap=no",
        "displacement=0.0472",
        "rejection=0.5333",
        "followThrough=0.4018",
        "Derived from daily resistance swing.",
        "displacement=0.1017",
        "rejection=0.3113",
        "followThrough=0.5947",
        "gapContinuation=0.3246",
        "displacement=0.0697",
        "rejection=0.5289",
        "followThrough=0.7070",
        "gapContinuation=0.9948",
        "freshness=stale",
        "evidence=5",
        "rejection=0.4157",
        "followThrough=0.5571",
        "gapContinuation=0.4639",
        "pathClearance=0.7611",
        "crowdingPenalty=1.0000",
        "recycledPenalty=1.0000"
      ]
    }
  ],
  "intermediateSupport": [
    {
      "id": "AIM-support-zone-7",
      "symbol": "AIM",
      "kind": "support",
      "timeframeBias": "4h",
      "zoneLow": 0.27,
      "zoneHigh": 0.2707,
      "representativePrice": 0.2707,
      "strengthScore": 21.56,
      "strengthLabel": "moderate",
      "touchCount": 13,
      "confluenceCount": 1,
      "sourceTypes": [
        "swing_low"
      ],
      "timeframeSources": [
        "4h"
      ],
      "reactionQualityScore": 0.6466,
      "rejectionScore": 0.1497,
      "displacementScore": 0.185,
      "sessionSignificanceScore": 0.504,
      "followThroughScore": 0.4955,
      "gapContinuationScore": 0.5,
      "sourceEvidenceCount": 2,
      "firstTimestamp": 1778587200000,
      "lastTimestamp": 1778688000000,
      "isExtension": false,
      "freshness": "stale",
      "notes": [
        "Derived from 4h support swing.",
        "displacement=0.1253",
        "reactions=5",
        "rejection=0.0000",
        "followThrough=0.3036",
        "gapContinuation=0.0000",
        "gap=no",
        "displacement=0.2267",
        "reactions=4",
        "rejection=0.2993",
        "followThrough=0.6875",
        "gapContinuation=1.0000",
        "gap=yes",
        "freshness=stale",
        "evidence=2",
        "rejection=0.1497",
        "followThrough=0.4955",
        "gapContinuation=0.5000",
        "pathClearance=1.0000",
        "crowdingPenalty=1.0000",
        "recycledPenalty=1.0000"
      ]
    },
    {
      "id": "AIM-support-zone-6",
      "symbol": "AIM",
      "kind": "support",
      "timeframeBias": "4h",
      "zoneLow": 0.2503,
      "zoneHigh": 0.2503,
      "representativePrice": 0.2503,
      "strengthScore": 16.47,
      "strengthLabel": "moderate",
      "touchCount": 7,
      "confluenceCount": 1,
      "sourceTypes": [
        "swing_low"
      ],
      "timeframeSources": [
        "4h"
      ],
      "reactionQualityScore": 0.6687,
      "rejectionScore": 0.0756,
      "displacementScore": 0.1588,
      "sessionSignificanceScore": 0.5091,
      "followThroughScore": 0.5359,
      "gapContinuationScore": 0.8947,
      "sourceEvidenceCount": 1,
      "firstTimestamp": 1778774400000,
      "lastTimestamp": 1778774400000,
      "isExtension": false,
      "freshness": "stale",
      "notes": [
        "Derived from 4h support swing.",
        "displacement=0.1470",
        "reactions=4",
        "rejection=0.0756",
        "followThrough=0.5359",
        "gapContinuation=0.8947",
        "gap=yes",
        "freshness=stale",
        "evidence=1",
        "rejection=0.0756",
        "followThrough=0.5359",
        "gapContinuation=0.8947",
        "pathClearance=1.0000",
        "crowdingPenalty=1.0000",
        "recycledPenalty=1.0000"
      ]
    },
    {
      "id": "AIM-support-zone-4",
      "symbol": "AIM",
      "kind": "support",
      "timeframeBias": "4h",
      "zoneLow": 0.228,
      "zoneHigh": 0.228,
      "representativePrice": 0.228,
      "strengthScore": 16.11,
      "strengthLabel": "moderate",
      "touchCount": 3,
      "confluenceCount": 1,
      "sourceTypes": [
        "swing_low"
      ],
      "timeframeSources": [
        "4h"
      ],
      "reactionQualityScore": 0.4375,
      "rejectionScore": 0.0746,
      "displacementScore": 0.8986,
      "sessionSignificanceScore": 0.7046,
      "followThroughScore": 0.7539,
      "gapContinuationScore": 0,
      "sourceEvidenceCount": 1,
      "firstTimestamp": 1779868800000,
      "lastTimestamp": 1779868800000,
      "isExtension": false,
      "freshness": "aging",
      "notes": [
        "Derived from 4h support swing.",
        "displacement=0.8986",
        "reactions=2",
        "rejection=0.0746",
        "followThrough=0.7539",
        "gapContinuation=0.0000",
        "gap=no",
        "freshness=aging",
        "evidence=1",
        "rejection=0.0746",
        "followThrough=0.7539",
        "gapContinuation=0.0000",
        "pathClearance=0.3133",
        "crowdingPenalty=1.0000",
        "recycledPenalty=1.0000"
      ]
    },
    {
      "id": "AIM-support-zone-2",
      "symbol": "AIM",
      "kind": "support",
      "timeframeBias": "4h",
      "zoneLow": 0.2206,
      "zoneHigh": 0.2206,
      "representativePrice": 0.2206,
      "strengthScore": 13.4,
      "strengthLabel": "moderate",
      "touchCount": 1,
      "confluenceCount": 1,
      "sourceTypes": [
        "swing_low"
      ],
      "timeframeSources": [
        "4h"
      ],
      "reactionQualityScore": 0.3388,
      "rejectionScore": 0.5422,
      "displacementScore": 0.0863,
      "sessionSignificanceScore": 0.6917,
      "followThroughScore": 0.7782,
      "gapContinuationScore": 0,
      "sourceEvidenceCount": 1,
      "firstTimestamp": 1779796800000,
      "lastTimestamp": 1779796800000,
      "isExtension": false,
      "freshness": "aging",
      "notes": [
        "Derived from 4h support swing.",
        "displacement=0.0863",
        "reactions=1",
        "rejection=0.5422",
        "followThrough=0.7782",
        "gapContinuation=0.0000",
        "gap=no",
        "freshness=aging",
        "evidence=1",
        "rejection=0.5422",
        "followThrough=0.7782",
        "gapContinuation=0.0000",
        "pathClearance=1.0000",
        "crowdingPenalty=1.0000",
        "recycledPenalty=1.0000"
      ]
    }
  ],
  "intermediateResistance": [
    {
      "id": "AIM-resistance-zone-13",
      "symbol": "AIM",
      "kind": "resistance",
      "timeframeBias": "4h",
      "zoneLow": 0.5282,
      "zoneHigh": 0.5299,
      "representativePrice": 0.5299,
      "strengthScore": 26.23,
      "strengthLabel": "strong",
      "touchCount": 20,
      "confluenceCount": 1,
      "sourceTypes": [
        "swing_high"
      ],
      "timeframeSources": [
        "4h"
      ],
      "reactionQualityScore": 0.4602,
      "rejectionScore": 0.4508,
      "displacementScore": 0.0677,
      "sessionSignificanceScore": 0.504,
      "followThroughScore": 0.5012,
      "gapContinuationScore": 0.2967,
      "sourceEvidenceCount": 5,
      "firstTimestamp": 1776859200000,
      "lastTimestamp": 1777924800000,
      "isExtension": false,
      "freshness": "stale",
      "notes": [
        "Derived from 4h resistance swing.",
        "displacement=0.0531",
        "reactions=2",
        "rejection=0.2690",
        "followThrough=0.4168",
        "gapContinuation=0.3500",
        "gap=yes",
        "displacement=0.0941",
        "rejection=0.3016",
        "followThrough=0.7087",
        "gapContinuation=0.7833",
        "displacement=0.0842",
        "rejection=0.5994",
        "followThrough=0.5315",
        "gapContinuation=0.0000",
        "gap=no",
        "displacement=0.0381",
        "reactions=3",
        "rejection=0.7340",
        "followThrough=0.3666",
        "displacement=0.0529",
        "rejection=0.3500",
        "followThrough=0.4822",
        "freshness=stale",
        "evidence=5",
        "rejection=0.4508",
        "followThrough=0.5012",
        "gapContinuation=0.2967",
        "pathClearance=0.4928",
        "crowdingPenalty=1.0000",
        "recycledPenalty=1.0000"
      ]
    },
    {
      "id": "AIM-resistance-zone-12",
      "symbol": "AIM",
      "kind": "resistance",
      "timeframeBias": "4h",
      "zoneLow": 0.459,
      "zoneHigh": 0.459,
      "representativePrice": 0.459,
      "strengthScore": 9.86,
      "strengthLabel": "weak",
      "touchCount": 1,
      "confluenceCount": 1,
      "sourceTypes": [
        "swing_high"
      ],
      "timeframeSources": [
        "4h"
      ],
      "reactionQualityScore": 0.2169,
      "rejectionScore": 0.2539,
      "displacementScore": 0.804,
      "sessionSignificanceScore": 0.5991,
      "followThroughScore": 0.702,
      "gapContinuationScore": 0.2288,
      "sourceEvidenceCount": 1,
      "firstTimestamp": 1779278400000,
      "lastTimestamp": 1779278400000,
      "isExtension": false,
      "freshness": "stale",
      "notes": [
        "Derived from 4h resistance swing.",
        "displacement=0.7444",
        "reactions=1",
        "rejection=0.2539",
        "followThrough=0.7020",
        "gapContinuation=0.2288",
        "gap=yes",
        "freshness=stale",
        "evidence=1",
        "rejection=0.2539",
        "followThrough=0.7020",
        "gapContinuation=0.2288",
        "pathClearance=1.0000",
        "crowdingPenalty=1.0000",
        "recycledPenalty=1.0000"
      ]
    },
    {
      "id": "AIM-resistance-zone-11",
      "symbol": "AIM",
      "kind": "resistance",
      "timeframeBias": "4h",
      "zoneLow": 0.4282,
      "zoneHigh": 0.4282,
      "representativePrice": 0.4282,
      "strengthScore": 9.12,
      "strengthLabel": "weak",
      "touchCount": 1,
      "confluenceCount": 1,
      "sourceTypes": [
        "swing_high"
      ],
      "timeframeSources": [
        "4h"
      ],
      "reactionQualityScore": 0.1776,
      "rejectionScore": 0.1025,
      "displacementScore": 0.3361,
      "sessionSignificanceScore": 0.5863,
      "followThroughScore": 0.6356,
      "gapContinuationScore": 0,
      "sourceEvidenceCount": 1,
      "firstTimestamp": 1779206400000,
      "lastTimestamp": 1779206400000,
      "isExtension": false,
      "freshness": "stale",
      "notes": [
        "Derived from 4h resistance swing.",
        "displacement=0.3361",
        "reactions=1",
        "rejection=0.1025",
        "followThrough=0.6356",
        "gapContinuation=0.0000",
        "gap=no",
        "freshness=stale",
        "evidence=1",
        "rejection=0.1025",
        "followThrough=0.6356",
        "gapContinuation=0.0000",
        "pathClearance=1.0000",
        "crowdingPenalty=1.0000",
        "recycledPenalty=1.0000"
      ]
    }
  ],
  "intradaySupport": [
    {
      "id": "AIM-support-zone-13",
      "symbol": "AIM",
      "kind": "support",
      "timeframeBias": "5m",
      "zoneLow": 0.3492,
      "zoneHigh": 0.3518,
      "representativePrice": 0.35,
      "strengthScore": 50.33,
      "strengthLabel": "major",
      "touchCount": 88,
      "confluenceCount": 1,
      "sourceTypes": [
        "swing_low"
      ],
      "timeframeSources": [
        "5m"
      ],
      "reactionQualityScore": 0.8538,
      "rejectionScore": 0.323,
      "displacementScore": 0.0218,
      "sessionSignificanceScore": 0.3563,
      "followThroughScore": 0.0689,
      "gapContinuationScore": 0,
      "sourceEvidenceCount": 6,
      "firstTimestamp": 1779956400000,
      "lastTimestamp": 1779961500000,
      "isExtension": false,
      "freshness": "aging",
      "notes": [
        "Derived from 5m support swing.",
        "displacement=0.0105",
        "reactions=5",
        "rejection=0.0000",
        "followThrough=0.0207",
        "gapContinuation=0.0000",
        "gap=no",
        "displacement=0.0167",
        "reactions=1",
        "rejection=1.0000",
        "followThrough=0.3929",
        "displacement=0.0574",
        "reactions=7",
        "rejection=0.3500",
        "followThrough=0.0000",
        "displacement=0.0208",
        "reactions=11",
        "rejection=0.2222",
        "displacement=0.0127",
        "reactions=13",
        "rejection=0.3659",
        "freshness=aging",
        "evidence=6",
        "rejection=0.3230",
        "followThrough=0.0689",
        "gapContinuation=0.0000",
        "pathClearance=1.0000",
        "crowdingPenalty=1.0000",
        "recycledPenalty=0.8400"
      ]
    },
    {
      "id": "AIM-support-zone-11",
      "symbol": "AIM",
      "kind": "support",
      "timeframeBias": "5m",
      "zoneLow": 0.327,
      "zoneHigh": 0.331,
      "representativePrice": 0.33,
      "strengthScore": 25.51,
      "strengthLabel": "strong",
      "touchCount": 23,
      "confluenceCount": 1,
      "sourceTypes": [
        "swing_low"
      ],
      "timeframeSources": [
        "5m"
      ],
      "reactionQualityScore": 0.8507,
      "rejectionScore": 0.3703,
      "displacementScore": 0.0554,
      "sessionSignificanceScore": 0.4331,
      "followThroughScore": 0.4633,
      "gapContinuationScore": 0.1659,
      "sourceEvidenceCount": 3,
      "firstTimestamp": 1779963600000,
      "lastTimestamp": 1779973800000,
      "isExtension": false,
      "freshness": "aging",
      "notes": [
        "Derived from 5m support swing.",
        "displacement=0.0849",
        "reactions=4",
        "rejection=0.0000",
        "followThrough=0.5942",
        "gapContinuation=0.4976",
        "gap=yes",
        "displacement=0.0310",
        "reactions=5",
        "rejection=0.9025",
        "followThrough=0.3179",
        "gapContinuation=0.0000",
        "gap=no",
        "displacement=0.0434",
        "rejection=0.2083",
        "followThrough=0.4777",
        "freshness=aging",
        "evidence=3",
        "rejection=0.3703",
        "followThrough=0.4633",
        "gapContinuation=0.1659",
        "pathClearance=1.0000",
        "crowdingPenalty=1.0000",
        "recycledPenalty=1.0000"
      ]
    },
    {
      "id": "AIM-support-zone-10",
      "symbol": "AIM",
      "kind": "support",
      "timeframeBias": "5m",
      "zoneLow": 0.32,
      "zoneHigh": 0.3238,
      "representativePrice": 0.32,
      "strengthScore": 23.22,
      "strengthLabel": "moderate",
      "touchCount": 17,
      "confluenceCount": 1,
      "sourceTypes": [
        "premarket_low",
        "swing_low"
      ],
      "timeframeSources": [
        "5m"
      ],
      "reactionQualityScore": 0.6843,
      "rejectionScore": 0.4665,
      "displacementScore": 0.1902,
      "sessionSignificanceScore": 1,
      "followThroughScore": 0.5971,
      "gapContinuationScore": 0,
      "sourceEvidenceCount": 4,
      "firstTimestamp": 1779955200000,
      "lastTimestamp": 1779976500000,
      "isExtension": false,
      "freshness": "aging",
      "notes": [
        "Session-accurate premarket low candidate.",
        "Derived from 5m support swing.",
        "displacement=0.0788",
        "reactions=1",
        "rejection=0.5561",
        "followThrough=0.6538",
        "gapContinuation=0.0000",
        "gap=no",
        "displacement=0.0480",
        "reactions=2",
        "rejection=0.0980",
        "followThrough=0.6091",
        "displacement=0.0340",
        "reactions=5",
        "rejection=0.5620",
        "followThrough=0.4056",
        "freshness=aging",
        "evidence=4",
        "rejection=0.4665",
        "followThrough=0.5971",
        "gapContinuation=0.0000",
        "pathClearance=1.0000",
        "crowdingPenalty=1.0000",
        "recycledPenalty=1.0000"
      ]
    }
  ],
  "intradayResistance": [
    {
      "id": "AIM-resistance-zone-9",
      "symbol": "AIM",
      "kind": "resistance",
      "timeframeBias": "5m",
      "zoneLow": 0.375,
      "zoneHigh": 0.375,
      "representativePrice": 0.375,
      "strengthScore": 12.96,
      "strengthLabel": "moderate",
      "touchCount": 4,
      "confluenceCount": 1,
      "sourceTypes": [
        "swing_high",
        "opening_range_high"
      ],
      "timeframeSources": [
        "5m"
      ],
      "reactionQualityScore": 0.6851,
      "rejectionScore": 0.4623,
      "displacementScore": 0.3916,
      "sessionSignificanceScore": 1,
      "followThroughScore": 0.7794,
      "gapContinuationScore": 0,
      "sourceEvidenceCount": 2,
      "firstTimestamp": 1779975000000,
      "lastTimestamp": 1779976500000,
      "isExtension": false,
      "freshness": "aging",
      "notes": [
        "Derived from 5m resistance swing.",
        "displacement=0.0833",
        "reactions=2",
        "rejection=0.2047",
        "followThrough=0.7388",
        "gapContinuation=0.0000",
        "gap=no",
        "Session-accurate opening range high candidate.",
        "freshness=aging",
        "evidence=2",
        "rejection=0.4623",
        "followThrough=0.7794",
        "gapContinuation=0.0000",
        "pathClearance=1.0000",
        "crowdingPenalty=1.0000",
        "recycledPenalty=1.0000"
      ]
    },
    {
      "id": "AIM-resistance-zone-10",
      "symbol": "AIM",
      "kind": "resistance",
      "timeframeBias": "5m",
      "zoneLow": 0.42,
      "zoneHigh": 0.42,
      "representativePrice": 0.42,
      "strengthScore": 9.65,
      "strengthLabel": "weak",
      "touchCount": 1,
      "confluenceCount": 1,
      "sourceTypes": [
        "premarket_high"
      ],
      "timeframeSources": [
        "5m"
      ],
      "reactionQualityScore": 0.8,
      "rejectionScore": 0.65,
      "displacementScore": 0.6,
      "sessionSignificanceScore": 1,
      "followThroughScore": 0.72,
      "gapContinuationScore": 0,
      "sourceEvidenceCount": 1,
      "firstTimestamp": 1779955200000,
      "lastTimestamp": 1779976500000,
      "isExtension": false,
      "freshness": "aging",
      "notes": [
        "Session-accurate premarket high candidate.",
        "freshness=aging",
        "evidence=1",
        "rejection=0.6500",
        "followThrough=0.7200",
        "gapContinuation=0.0000",
        "pathClearance=1.0000",
        "crowdingPenalty=1.0000",
        "recycledPenalty=1.0000"
      ]
    }
  ],
  "extensionLevels": {
    "support": [
      {
        "id": "AIM-support-zone-12",
        "symbol": "AIM",
        "kind": "support",
        "timeframeBias": "5m",
        "zoneLow": 0.3391,
        "zoneHigh": 0.3391,
        "representativePrice": 0.3391,
        "strengthScore": 10.04,
        "strengthLabel": "weak",
        "touchCount": 1,
        "confluenceCount": 1,
        "sourceTypes": [
          "opening_range_low"
        ],
        "timeframeSources": [
          "5m"
        ],
        "reactionQualityScore": 0.9,
        "rejectionScore": 0.72,
        "displacementScore": 0.7,
        "sessionSignificanceScore": 1,
        "followThroughScore": 0.82,
        "gapContinuationScore": 0,
        "sourceEvidenceCount": 1,
        "firstTimestamp": 1779975000000,
        "lastTimestamp": 1779976500000,
        "isExtension": true,
        "freshness": "aging",
        "notes": [
          "Session-accurate opening range low candidate.",
          "freshness=aging",
          "evidence=1",
          "rejection=0.7200",
          "followThrough=0.8200",
          "gapContinuation=0.0000",
          "pathClearance=1.0000",
          "crowdingPenalty=1.0000",
          "recycledPenalty=1.0000"
        ]
      },
      {
        "id": "AIM-support-zone-9",
        "symbol": "AIM",
        "kind": "support",
        "timeframeBias": "4h",
        "zoneLow": 0.2858,
        "zoneHigh": 0.2858,
        "representativePrice": 0.2858,
        "strengthScore": 9.44,
        "strengthLabel": "weak",
        "touchCount": 1,
        "confluenceCount": 1,
        "sourceTypes": [
          "swing_low"
        ],
        "timeframeSources": [
          "4h"
        ],
        "reactionQualityScore": 0.1891,
        "rejectionScore": 0.4457,
        "displacementScore": 0.2482,
        "sessionSignificanceScore": 0.504,
        "followThroughScore": 0.7593,
        "gapContinuationScore": 1,
        "sourceEvidenceCount": 1,
        "firstTimestamp": 1778500800000,
        "lastTimestamp": 1778500800000,
        "isExtension": true,
        "freshness": "stale",
        "notes": [
          "Derived from 4h support swing.",
          "displacement=0.2298",
          "reactions=1",
          "rejection=0.4457",
          "followThrough=0.7593",
          "gapContinuation=1.0000",
          "gap=yes",
          "freshness=stale",
          "evidence=1",
          "rejection=0.4457",
          "followThrough=0.7593",
          "gapContinuation=1.0000",
          "pathClearance=0.2899",
          "crowdingPenalty=1.0000",
          "recycledPenalty=1.0000"
        ]
      },
      {
        "id": "AIM-support-zone-8",
        "symbol": "AIM",
        "kind": "support",
        "timeframeBias": "4h",
        "zoneLow": 0.2829,
        "zoneHigh": 0.2829,
        "representativePrice": 0.2829,
        "strengthScore": 10.27,
        "strengthLabel": "weak",
        "touchCount": 1,
        "confluenceCount": 1,
        "sourceTypes": [
          "swing_low"
        ],
        "timeframeSources": [
          "4h"
        ],
        "reactionQualityScore": 0.1713,
        "rejectionScore": 0.3564,
        "displacementScore": 0.7437,
        "sessionSignificanceScore": 0.504,
        "followThroughScore": 0.7521,
        "gapContinuationScore": 1,
        "sourceEvidenceCount": 1,
        "firstTimestamp": 1778241600000,
        "lastTimestamp": 1778241600000,
        "isExtension": true,
        "freshness": "stale",
        "notes": [
          "Derived from 4h support swing.",
          "displacement=0.6886",
          "reactions=1",
          "rejection=0.3564",
          "followThrough=0.7521",
          "gapContinuation=1.0000",
          "gap=yes",
          "freshness=stale",
          "evidence=1",
          "rejection=0.3564",
          "followThrough=0.7521",
          "gapContinuation=1.0000",
          "pathClearance=1.0000",
          "crowdingPenalty=1.0000",
          "recycledPenalty=1.0000"
        ]
      }
    ],
    "resistance": []
  },
  "specialLevels": {
    "premarketHigh": 0.42,
    "premarketLow": 0.32,
    "openingRangeHigh": 0.375,
    "openingRangeLow": 0.3391
  }
}
